dcs/__init__.py
dcs/action.py
dcs/atcradio.py
dcs/beacons.py
dcs/cloud_presets.py
dcs/coalition.py
dcs/condition.py
dcs/countries.py
dcs/country.py
dcs/flyingunit.py
dcs/forcedoptions.py
dcs/goals.py
dcs/groundcontrol.py
dcs/helicopters.py
dcs/installation.py
dcs/liveries_scanner.py
dcs/mapping.py
dcs/mission.py
dcs/nav_target_point.py
dcs/payloads.py
dcs/planes.py
dcs/point.py
dcs/py.typed
dcs/ships.py
dcs/statics.py
dcs/status_message.py
dcs/task.py
dcs/templates.py
dcs/translation.py
dcs/triggers.py
dcs/unit.py
dcs/unitgroup.py
dcs/unittype.py
dcs/vehicles.py
dcs/weapons_data.py
dcs/weather.py
dcs/drawing/__init__.py
dcs/drawing/drawing.py
dcs/drawing/drawings.py
dcs/drawing/icon.py
dcs/drawing/layer.py
dcs/drawing/line.py
dcs/drawing/options.py
dcs/drawing/polygon.py
dcs/drawing/text_box.py
dcs/lua/__init__.py
dcs/lua/parse.py
dcs/lua/serialize.py
dcs/lua/test_parse.py
dcs/scripts/__init__.py
dcs/scripts/destroy_oil_transport.py
dcs/scripts/dogfight_wwii.py
dcs/scripts/nevada_random_mission.py
dcs/terrain/__init__.py
dcs/terrain/terrain.py
dcs/terrain/caucasus/__init__.py
dcs/terrain/caucasus/airports.py
dcs/terrain/caucasus/caucasus.py
dcs/terrain/caucasus/projection.py
dcs/terrain/falklands/__init__.py
dcs/terrain/falklands/airports.py
dcs/terrain/falklands/falklands.py
dcs/terrain/falklands/projection.py
dcs/terrain/marianaislands/__init__.py
dcs/terrain/marianaislands/airports.py
dcs/terrain/marianaislands/marianaislands.py
dcs/terrain/marianaislands/projection.py
dcs/terrain/nevada/__init__.py
dcs/terrain/nevada/airports.py
dcs/terrain/nevada/nevada.py
dcs/terrain/nevada/projection.py
dcs/terrain/normandy/__init__.py
dcs/terrain/normandy/airports.py
dcs/terrain/normandy/normandy.py
dcs/terrain/normandy/projection.py
dcs/terrain/persiangulf/__init__.py
dcs/terrain/persiangulf/airports.py
dcs/terrain/persiangulf/persiangulf.py
dcs/terrain/persiangulf/projection.py
dcs/terrain/projections/__init__.py
dcs/terrain/projections/transversemercator.py
pydcs-0.15.0.dist-info/LICENSE.txt
pydcs-0.15.0.dist-info/METADATA
pydcs-0.15.0.dist-info/WHEEL
pydcs-0.15.0.dist-info/entry_points.txt
pydcs-0.15.0.dist-info/top_level.txt
pydcs-0.15.0.dist-info/RECORD
