Metadata-Version: 2.1
Name: pydcs
Version: 0.15.0
Summary: A Digital Combat Simulator mission builder framework
Home-page: https://github.com/pydcs/dcs
Author: Peinthor Rene
Author-email: peinthor@gmail.com
License: LGPLv3
Keywords: dcs digital combat simulator eagle dynamics mission framework
Classifier: Development Status :: 4 - Beta
Classifier: Topic :: Games/Entertainment :: Simulation
Classifier: Intended Audience :: Developers
Classifier: Intended Audience :: End Users/Desktop
Classifier: License :: OSI Approved :: GNU Lesser General Public License v3 (LGPLv3)
Classifier: Programming Language :: Python :: 3.7
Classifier: Programming Language :: Python :: 3.8
Classifier: Programming Language :: Python :: 3.9
Classifier: Programming Language :: Python :: 3.10
Classifier: Programming Language :: Python :: 3.11
Classifier: Programming Language :: Python :: 3 :: Only
License-File: LICENSE.txt
Requires-Dist: pyproj
